[{"id":"6282183317888@s.whatsapp.net","xp":1,"level":1},{"id":"6285159551629@s.whatsapp.net","xp":1,"level":1},{"id":"6285368236665@s.whatsapp.net","xp":1,"level":1},{"id":"62895363196328@s.whatsapp.net","xp":1,"level":1},{"id":"6287810115807@s.whatsapp.net","xp":1,"level":1},{"id":"6287810115807@s.whatsapp.net","xp":1.00001000258278e+29,"level":100000000000001540},{"id":"628986944313@s.whatsapp.net","xp":1,"level":1},{"id":"628986944313@s.whatsapp.net","xp":964137,"level":8},{"id":"6289656939477@s.whatsapp.net","xp":1,"level":1},{"id":"6289656939477@s.whatsapp.net","xp":1627920,"level":1000000},{"id":"6285800199301@s.whatsapp.net","xp":1,"level":1},{"id":"6285800199301@s.whatsapp.net","xp":877240,"level":8},{"id":"6282171484214@s.whatsapp.net","xp":1,"level":1},{"id":"6282171484214@s.whatsapp.net","xp":1038047,"level":8},{"id":"6282364670355@s.whatsapp.net","xp":1,"level":1},{"id":"6282364670355@s.whatsapp.net","xp":63058,"level":4},{"id":"6285706666210@s.whatsapp.net","xp":1,"level":1},{"id":"6285706666210@s.whatsapp.net","xp":833204,"level":8},{"id":"6282256082934@s.whatsapp.net","xp":1,"level":1},{"id":"6282256082934@s.whatsapp.net","xp":3036459,"level":10},{"id":"6285267951470@s.whatsapp.net","xp":1,"level":1},{"id":"6285267951470@s.whatsapp.net","xp":271962,"level":6},{"id":"6287788782867@s.whatsapp.net","xp":1,"level":1},{"id":"6287788782867@s.whatsapp.net","xp":568831,"level":7},{"id":"6282320700027@s.whatsapp.net","xp":1,"level":1},{"id":"6282320700027@s.whatsapp.net","xp":205171,"level":6},{"id":"6285712075837@s.whatsapp.net","xp":1,"level":1},{"id":"6285712075837@s.whatsapp.net","xp":1428045,"level":9},{"id":"6281225600224@s.whatsapp.net","xp":1,"level":1},{"id":"6281225600224@s.whatsapp.net","xp":2674,"level":1},{"id":"6281350608933@s.whatsapp.net","xp":1,"level":1},{"id":"6281350608933@s.whatsapp.net","xp":667818,"level":8},{"id":"6288806636219@s.whatsapp.net","xp":1,"level":1},{"id":"6288806636219@s.whatsapp.net","xp":64726,"level":4},{"id":"6281381606682@s.whatsapp.net","xp":1,"level":1},{"id":"6281381606682@s.whatsapp.net","xp":493317,"level":7},{"id":"6281393958147@s.whatsapp.net","xp":1,"level":1},{"id":"6281393958147@s.whatsapp.net","xp":3030,"level":1},{"id":"628971630781@s.whatsapp.net","xp":1,"level":1},{"id":"628971630781@s.whatsapp.net","xp":929650,"level":8},{"id":"6282233222275@s.whatsapp.net","xp":29237,"level":3},{"id":"6281285206570@s.whatsapp.net","xp":1,"level":1},{"id":"6281285206570@s.whatsapp.net","xp":24213,"level":3},{"id":"6281233877650@s.whatsapp.net","xp":1,"level":1},{"id":"6281233877650@s.whatsapp.net","xp":366798,"level":7},{"id":"6285326654123@s.whatsapp.net","xp":1,"level":1},{"id":"6285326654123@s.whatsapp.net","xp":9067,"level":2},{"id":"6289646562691@s.whatsapp.net","xp":1,"level":1},{"id":"6289646562691@s.whatsapp.net","xp":19205,"level":3},{"id":"6281351853995@s.whatsapp.net","xp":1,"level":1},{"id":"6285821828766@s.whatsapp.net","xp":1,"level":1},{"id":"62895347922002@s.whatsapp.net","xp":1,"level":1},{"id":"62895347922002@s.whatsapp.net","xp":1187286,"level":8},{"id":"6281267439077@s.whatsapp.net","xp":1,"level":1},{"id":"6281267439077@s.whatsapp.net","xp":656870,"level":8},{"id":"6287819833137@s.whatsapp.net","xp":1,"level":1},{"id":"6287819833137@s.whatsapp.net","xp":624427,"level":7},{"id":"601139259687@s.whatsapp.net","xp":1,"level":1},{"id":"601139259687@s.whatsapp.net","xp":20687,"level":3},{"id":"6285831126131@s.whatsapp.net","xp":1,"level":1},{"id":"6285831126131@s.whatsapp.net","xp":8593,"level":2},{"id":"6285761519741@s.whatsapp.net","xp":1,"level":1},{"id":"6285761519741@s.whatsapp.net","xp":16150,"level":3},{"id":"6282188250312@s.whatsapp.net","xp":1,"level":1},{"id":"6282188250312@s.whatsapp.net","xp":80757,"level":5},{"id":"6285781494841@s.whatsapp.net","xp":1,"level":1},{"id":"6285781494841@s.whatsapp.net","xp":334784,"level":7},{"id":"628979200450@s.whatsapp.net","xp":1,"level":1},{"id":"628979200450@s.whatsapp.net","xp":247205,"level":6},{"id":"60169314295@s.whatsapp.net","xp":1,"level":1},{"id":"60169314295@s.whatsapp.net","xp":95898,"level":5},{"id":"6285342522658@s.whatsapp.net","xp":1,"level":1},{"id":"6285342522658@s.whatsapp.net","xp":32786,"level":3},{"id":"6285609818050@s.whatsapp.net","xp":1,"level":1},{"id":"6285609818050@s.whatsapp.net","xp":73111,"level":4},{"id":"6287802476426@s.whatsapp.net","xp":1,"level":1},{"id":"6287802476426@s.whatsapp.net","xp":54964,"level":4},{"id":"6285345744859@s.whatsapp.net","xp":1,"level":1},{"id":"6285345744859@s.whatsapp.net","xp":8051,"level":2},{"id":"6282151021628@s.whatsapp.net","xp":1,"level":1},{"id":"6282151021628@s.whatsapp.net","xp":6545,"level":2},{"id":"6282115344818@s.whatsapp.net","xp":1,"level":1},{"id":"6282115344818@s.whatsapp.net","xp":194251,"level":6},{"id":"6281260740466@s.whatsapp.net","xp":1,"level":1},{"id":"6281260740466@s.whatsapp.net","xp":381342,"level":7},{"id":"62895601231122@s.whatsapp.net","xp":1,"level":1},{"id":"62895601231122@s.whatsapp.net","xp":99361,"level":5},{"id":"6282242494751@s.whatsapp.net","xp":1,"level":1},{"id":"6282242494751@s.whatsapp.net","xp":80522,"level":5},{"id":"6289652543706@s.whatsapp.net","xp":1,"level":1},{"id":"6283824271834@s.whatsapp.net","xp":1,"level":1},{"id":"6283824271834@s.whatsapp.net","xp":43783,"level":4},{"id":"6285269364656@s.whatsapp.net","xp":1,"level":1},{"id":"6285269364656@s.whatsapp.net","xp":14139,"level":2},{"id":"6281317153744@s.whatsapp.net","xp":1,"level":1},{"id":"6281317153744@s.whatsapp.net","xp":1018,"level":1},{"id":"6283106395801@s.whatsapp.net","xp":1,"level":1},{"id":"6283106395801@s.whatsapp.net","xp":29298,"level":3},{"id":"6282137281256@s.whatsapp.net","xp":1,"level":1},{"id":"6282137281256@s.whatsapp.net","xp":245223,"level":6},{"id":"6281341940735@s.whatsapp.net","xp":1,"level":1},{"id":"6281341940735@s.whatsapp.net","xp":446087,"level":7},{"id":"62881036663514@s.whatsapp.net","xp":1,"level":1},{"id":"62881036663514@s.whatsapp.net","xp":976930,"level":8},{"id":"6283170750405@s.whatsapp.net","xp":1,"level":1},{"id":"6283170750405@s.whatsapp.net","xp":47891,"level":4},{"id":"6285212227734@s.whatsapp.net","xp":1,"level":1},{"id":"6285212227734@s.whatsapp.net","xp":6053,"level":2},{"id":"6285850757619@s.whatsapp.net","xp":506,"level":1},{"id":"6285850757619@s.whatsapp.net","xp":1,"level":1},{"id":"6285850757619@s.whatsapp.net","xp":4044,"level":1},{"id":"62895396271278@s.whatsapp.net","xp":1,"level":1},{"id":"62895396271278@s.whatsapp.net","xp":6558,"level":2},{"id":"6285317266350@s.whatsapp.net","xp":502,"level":1},{"id":"6285317266350@s.whatsapp.net","xp":1,"level":1},{"id":"6285317266350@s.whatsapp.net","xp":278013,"level":6},{"id":"6285878446260@s.whatsapp.net","xp":1,"level":1},{"id":"6282258414576@s.whatsapp.net","xp":1,"level":1},{"id":"6282258414576@s.whatsapp.net","xp":19670,"level":3},{"id":"6283154509292@s.whatsapp.net","xp":1,"level":1},{"id":"6283154509292@s.whatsapp.net","xp":589934,"level":7},{"id":"6281289730926@s.whatsapp.net","xp":1,"level":1},{"id":"6281289730926@s.whatsapp.net","xp":83717,"level":5},{"id":"6289685876775@s.whatsapp.net","xp":1,"level":1},{"id":"6289685876775@s.whatsapp.net","xp":7076,"level":2},{"id":"6283155407945@s.whatsapp.net","xp":1,"level":1},{"id":"6283155407945@s.whatsapp.net","xp":2019,"level":1},{"id":"62895620102738@s.whatsapp.net","xp":1,"level":1},{"id":"62895620102738@s.whatsapp.net","xp":19184,"level":3},{"id":"6285864827915@s.whatsapp.net","xp":1,"level":1},{"id":"6285864827915@s.whatsapp.net","xp":1009,"level":1},{"id":"6285832733831@s.whatsapp.net","xp":1,"level":1},{"id":"6285832733831@s.whatsapp.net","xp":211984,"level":6},{"id":"62859102673622@s.whatsapp.net","xp":1,"level":1},{"id":"62859102673622@s.whatsapp.net","xp":140762,"level":5},{"id":"6283871471121@s.whatsapp.net","xp":1,"level":1},{"id":"6283871471121@s.whatsapp.net","xp":119229,"level":5},{"id":"6283112856067@s.whatsapp.net","xp":4546,"level":1},{"id":"62895323039721@s.whatsapp.net","xp":1,"level":1},{"id":"62895323039721@s.whatsapp.net","xp":40394,"level":4},{"id":"6281804519208@s.whatsapp.net","xp":1,"level":1},{"id":"6281804519208@s.whatsapp.net","xp":127205,"level":5},{"id":"6281220597592@s.whatsapp.net","xp":1,"level":1},{"id":"6281220597592@s.whatsapp.net","xp":5047,"level":2},{"id":"6281229108199@s.whatsapp.net","xp":1,"level":1},{"id":"6281229108199@s.whatsapp.net","xp":10088,"level":2},{"id":"6289648943220@s.whatsapp.net","xp":1,"level":1},{"id":"6289648943220@s.whatsapp.net","xp":2530,"level":1},{"id":"6285266728063@s.whatsapp.net","xp":1,"level":1},{"id":"6285266728063@s.whatsapp.net","xp":82109,"level":5},{"id":"6289519510364@s.whatsapp.net","xp":1,"level":1},{"id":"6289519510364@s.whatsapp.net","xp":467374,"level":7},{"id":"6287830672779@s.whatsapp.net","xp":368564,"level":7},{"id":"6288228919670@s.whatsapp.net","xp":1,"level":1},{"id":"6288228919670@s.whatsapp.net","xp":2018,"level":1},{"id":"628978551438@s.whatsapp.net","xp":1,"level":1},{"id":"628978551438@s.whatsapp.net","xp":70791,"level":4},{"id":"6285278752575@s.whatsapp.net","xp":1,"level":1},{"id":"6285278752575@s.whatsapp.net","xp":119743,"level":5},{"id":"6285751202084@s.whatsapp.net","xp":1,"level":1},{"id":"6285751202084@s.whatsapp.net","xp":242053,"level":6},{"id":"6287867786519@s.whatsapp.net","xp":1,"level":1},{"id":"6287867786519@s.whatsapp.net","xp":34801,"level":3},{"id":"6283101126595@s.whatsapp.net","xp":39338,"level":4},{"id":"6282233304782@s.whatsapp.net","xp":1,"level":1},{"id":"6282233304782@s.whatsapp.net","xp":3537,"level":1},{"id":"6281913868592@s.whatsapp.net","xp":1,"level":1},{"id":"6281913868592@s.whatsapp.net","xp":4553,"level":1},{"id":"6282315795986@s.whatsapp.net","xp":1,"level":1},{"id":"6282315795986@s.whatsapp.net","xp":3524,"level":1},{"id":"6285649571546@s.whatsapp.net","xp":1,"level":1},{"id":"6285649571546@s.whatsapp.net","xp":21684,"level":3},{"id":"6283196953942@s.whatsapp.net","xp":1,"level":1},{"id":"6283196953942@s.whatsapp.net","xp":506,"level":1},{"id":"62895634420918@s.whatsapp.net","xp":1,"level":1},{"id":"62895634420918@s.whatsapp.net","xp":77020,"level":5},{"id":"6285883632375@s.whatsapp.net","xp":1,"level":1},{"id":"6283837003853@s.whatsapp.net","xp":1,"level":1},{"id":"6283837003853@s.whatsapp.net","xp":393575,"level":7},{"id":"6282291158908@s.whatsapp.net","xp":1,"level":1},{"id":"6282291158908@s.whatsapp.net","xp":68124,"level":4},{"id":"6285766255448@s.whatsapp.net","xp":1,"level":1},{"id":"6285766255448@s.whatsapp.net","xp":13623,"level":2},{"id":"6281234687267@s.whatsapp.net","xp":1,"level":1},{"id":"6281234687267@s.whatsapp.net","xp":1014,"level":1},{"id":"6282117114620@s.whatsapp.net","xp":1,"level":1},{"id":"6282117114620@s.whatsapp.net","xp":331846,"level":7},{"id":"62895402605644@s.whatsapp.net","xp":63062,"level":4},{"id":"6282316503878@s.whatsapp.net","xp":1,"level":1},{"id":"6282316503878@s.whatsapp.net","xp":90743,"level":5},{"id":"6285640632566@s.whatsapp.net","xp":1,"level":1},{"id":"6285640632566@s.whatsapp.net","xp":2524,"level":1},{"id":"6285830124354@s.whatsapp.net","xp":1,"level":1},{"id":"6285830124354@s.whatsapp.net","xp":78129,"level":4},{"id":"6283892608617@s.whatsapp.net","xp":1,"level":1},{"id":"6283892608617@s.whatsapp.net","xp":4539,"level":1},{"id":"6281389049819@s.whatsapp.net","xp":1,"level":1},{"id":"6281389049819@s.whatsapp.net","xp":322032,"level":7},{"id":"6281539815687@s.whatsapp.net","xp":1,"level":1},{"id":"6281539815687@s.whatsapp.net","xp":7060,"level":2},{"id":"62895326114240@s.whatsapp.net","xp":1,"level":1},{"id":"62895326114240@s.whatsapp.net","xp":20687,"level":3},{"id":"6283895154439@s.whatsapp.net","xp":1,"level":1},{"id":"6283895154439@s.whatsapp.net","xp":15627,"level":3},{"id":"6281217461440@s.whatsapp.net","xp":1,"level":1},{"id":"6281217461440@s.whatsapp.net","xp":17162,"level":3},{"id":"6285849499824@s.whatsapp.net","xp":1,"level":1},{"id":"6285849499824@s.whatsapp.net","xp":40338,"level":4},{"id":"6283125945475@s.whatsapp.net","xp":1,"level":1},{"id":"6283125945475@s.whatsapp.net","xp":68385,"level":4},{"id":"6282157101279@s.whatsapp.net","xp":1,"level":1},{"id":"6282157101279@s.whatsapp.net","xp":11604,"level":2},{"id":"6281312615017@s.whatsapp.net","xp":1,"level":1},{"id":"6281312615017@s.whatsapp.net","xp":93899,"level":5},{"id":"6282160954444@s.whatsapp.net","xp":1,"level":1},{"id":"6282160954444@s.whatsapp.net","xp":729791,"level":8},{"id":"6285155433287@s.whatsapp.net","xp":1,"level":1},{"id":"6285155433287@s.whatsapp.net","xp":4547,"level":1},{"id":"6285388585857@s.whatsapp.net","xp":137670,"level":5},{"id":"6285227245333@s.whatsapp.net","xp":1,"level":1},{"id":"6285227245333@s.whatsapp.net","xp":23703,"level":3},{"id":"6281917707408@s.whatsapp.net","xp":1,"level":1},{"id":"6281917707408@s.whatsapp.net","xp":10610,"level":2},{"id":"6289637028853@s.whatsapp.net","xp":1,"level":1},{"id":"6289637028853@s.whatsapp.net","xp":68090,"level":4},{"id":"6282257902854@s.whatsapp.net","xp":1519,"level":1},{"id":"6282257902854@s.whatsapp.net","xp":1,"level":1},{"id":"6282257902854@s.whatsapp.net","xp":9612,"level":2},{"id":"6282192423343@s.whatsapp.net","xp":1,"level":1},{"id":"6282192423343@s.whatsapp.net","xp":3537,"level":1},{"id":"6282181041052@s.whatsapp.net","xp":1,"level":1},{"id":"6285379564038@s.whatsapp.net","xp":1,"level":1},{"id":"6285379564038@s.whatsapp.net","xp":40155,"level":4},{"id":"6282228027890@s.whatsapp.net","xp":1,"level":1},{"id":"6282228027890@s.whatsapp.net","xp":83695,"level":5},{"id":"6282157836779@s.whatsapp.net","xp":1,"level":1},{"id":"6282157836779@s.whatsapp.net","xp":418256,"level":7},{"id":"6285294988684@s.whatsapp.net","xp":1,"level":1},{"id":"6285294988684@s.whatsapp.net","xp":17172,"level":3},{"id":"6282123666331@s.whatsapp.net","xp":1,"level":1},{"id":"6282123666331@s.whatsapp.net","xp":220024,"level":6},{"id":"628881530749@s.whatsapp.net","xp":1,"level":1},{"id":"628881530749@s.whatsapp.net","xp":13621,"level":2},{"id":"6283816100374@s.whatsapp.net","xp":1,"level":1},{"id":"6283816100374@s.whatsapp.net","xp":101365,"level":5},{"id":"628975333383@s.whatsapp.net","xp":1,"level":1},{"id":"628975333383@s.whatsapp.net","xp":24204,"level":3},{"id":"62895625458050@s.whatsapp.net","xp":1,"level":1},{"id":"62895625458050@s.whatsapp.net","xp":102858,"level":5},{"id":"6281348359531@s.whatsapp.net","xp":1,"level":1},{"id":"6281348359531@s.whatsapp.net","xp":17928,"level":3},{"id":"6283846457752@s.whatsapp.net","xp":1,"level":1},{"id":"6283846457752@s.whatsapp.net","xp":141433,"level":5},{"id":"62895619126246@s.whatsapp.net","xp":505,"level":1},{"id":"62895619126246@s.whatsapp.net","xp":1,"level":1},{"id":"62895619126246@s.whatsapp.net","xp":345562,"level":7},{"id":"6288271064358@s.whatsapp.net","xp":1,"level":1},{"id":"6288271064358@s.whatsapp.net","xp":1005,"level":1},{"id":"6282282386405@s.whatsapp.net","xp":1,"level":1},{"id":"6282282386405@s.whatsapp.net","xp":8068,"level":2},{"id":"6283803586006@s.whatsapp.net","xp":1,"level":1},{"id":"6283803586006@s.whatsapp.net","xp":2524,"level":1},{"id":"6285732434622@s.whatsapp.net","xp":1,"level":1},{"id":"6285732434622@s.whatsapp.net","xp":48425,"level":4},{"id":"6281910116424@s.whatsapp.net","xp":37339,"level":4},{"id":"6281241557202@s.whatsapp.net","xp":1,"level":1},{"id":"6281241557202@s.whatsapp.net","xp":35790,"level":4},{"id":"6289669760942@s.whatsapp.net","xp":1,"level":1},{"id":"6289669760942@s.whatsapp.net","xp":72618,"level":4},{"id":"6283178837005@s.whatsapp.net","xp":1,"level":1},{"id":"6283178837005@s.whatsapp.net","xp":1,"level":1},{"id":"6285700249591@s.whatsapp.net","xp":1,"level":1},{"id":"6285700249591@s.whatsapp.net","xp":507,"level":1},{"id":"6285711842131@s.whatsapp.net","xp":1,"level":1},{"id":"6285711842131@s.whatsapp.net","xp":501,"level":1},{"id":"6285242487069@s.whatsapp.net","xp":503,"level":1},{"id":"6285242487069@s.whatsapp.net","xp":1,"level":1},{"id":"6285242487069@s.whatsapp.net","xp":18652,"level":3},{"id":"60139550568@s.whatsapp.net","xp":1,"level":1},{"id":"60139550568@s.whatsapp.net","xp":42923,"level":4},{"id":"6287759838973@s.whatsapp.net","xp":1,"level":1},{"id":"6287759838973@s.whatsapp.net","xp":905403,"level":8},{"id":"6289508703658@s.whatsapp.net","xp":1,"level":1},{"id":"6289508703658@s.whatsapp.net","xp":43733,"level":4},{"id":"6285747439671@s.whatsapp.net","xp":1,"level":1},{"id":"6285747439671@s.whatsapp.net","xp":27243,"level":3},{"id":"6285524999368@s.whatsapp.net","xp":1,"level":1},{"id":"6285524999368@s.whatsapp.net","xp":508,"level":1},{"id":"6285926115743@s.whatsapp.net","xp":1,"level":1},{"id":"6285926115743@s.whatsapp.net","xp":263787,"level":6},{"id":"6289517414764@s.whatsapp.net","xp":1,"level":1},{"id":"6289517414764@s.whatsapp.net","xp":25729,"level":3},{"id":"6285846695165@s.whatsapp.net","xp":1,"level":1},{"id":"6281994665353@s.whatsapp.net","xp":1,"level":1},{"id":"6281994665353@s.whatsapp.net","xp":17154,"level":3},{"id":"6283875015399@s.whatsapp.net","xp":1,"level":1},{"id":"62895336417781@s.whatsapp.net","xp":1,"level":1},{"id":"62895336417781@s.whatsapp.net","xp":65031,"level":4},{"id":"6282287321785@s.whatsapp.net","xp":1,"level":1},{"id":"6282287321785@s.whatsapp.net","xp":61586,"level":4},{"id":"6285725251834@s.whatsapp.net","xp":1,"level":1},{"id":"6285725251834@s.whatsapp.net","xp":504,"level":1},{"id":"6281393500655@s.whatsapp.net","xp":1,"level":1},{"id":"6281393500655@s.whatsapp.net","xp":31769,"level":3},{"id":"60135430840@s.whatsapp.net","xp":1,"level":1},{"id":"60135430840@s.whatsapp.net","xp":15631,"level":3},{"id":"6285238220103@s.whatsapp.net","xp":1,"level":1},{"id":"6285238220103@s.whatsapp.net","xp":18676,"level":3},{"id":"6281261544233@s.whatsapp.net","xp":1,"level":1},{"id":"6281261544233@s.whatsapp.net","xp":1520,"level":1},{"id":"6281272744259@s.whatsapp.net","xp":1,"level":1},{"id":"6281272744259@s.whatsapp.net","xp":28600,"level":3},{"id":"6281329367014@s.whatsapp.net","xp":1,"level":1},{"id":"6281329367014@s.whatsapp.net","xp":19722,"level":3},{"id":"6283853705588@s.whatsapp.net","xp":1,"level":1},{"id":"6283853705588@s.whatsapp.net","xp":503,"level":1},{"id":"62895399371903@s.whatsapp.net","xp":1,"level":1},{"id":"6287785623859@s.whatsapp.net","xp":1,"level":1},{"id":"6287785623859@s.whatsapp.net","xp":1005,"level":1},{"id":"6287778843979@s.whatsapp.net","xp":1,"level":1},{"id":"6287778843979@s.whatsapp.net","xp":2020,"level":1},{"id":"6287815843996@s.whatsapp.net","xp":1,"level":1},{"id":"6287815843996@s.whatsapp.net","xp":506,"level":1},{"id":"6281703032605@s.whatsapp.net","xp":1,"level":1},{"id":"6281703032605@s.whatsapp.net","xp":5035,"level":2},{"id":"6285751581406@s.whatsapp.net","xp":1,"level":1},{"id":"6285751581406@s.whatsapp.net","xp":395426,"level":7},{"id":"6282299864876@s.whatsapp.net","xp":1,"level":1},{"id":"6282299864876@s.whatsapp.net","xp":6572,"level":2},{"id":"62895803196379@s.whatsapp.net","xp":505,"level":1},{"id":"62895803196379@s.whatsapp.net","xp":1,"level":1},{"id":"62895803196379@s.whatsapp.net","xp":1015,"level":1},{"id":"62895602274694@s.whatsapp.net","xp":1,"level":1},{"id":"62895602274694@s.whatsapp.net","xp":1506,"level":1},{"id":"6281213841508@s.whatsapp.net","xp":1,"level":1},{"id":"6281213841508@s.whatsapp.net","xp":501,"level":1},{"id":"6288229421093@s.whatsapp.net","xp":1,"level":1},{"id":"6288229421093@s.whatsapp.net","xp":16662,"level":3},{"id":"62882003524608@s.whatsapp.net","xp":3017,"level":1},{"id":"6285742173810@s.whatsapp.net","xp":26242,"level":3},{"id":"6283151927226@s.whatsapp.net","xp":1,"level":1},{"id":"6283151927226@s.whatsapp.net","xp":502,"level":1},{"id":"6285156811194@s.whatsapp.net","xp":1,"level":1},{"id":"6285156811194@s.whatsapp.net","xp":1013,"level":1}]